jupyterlab_theme_christmas/__init__.py
jupyterlab_theme_christmas/_version.py
jupyterlab_theme_christmas/labextension/package.json
jupyterlab_theme_christmas/labextension/static/549.44cd2634f9cdc174fda1.js
jupyterlab_theme_christmas/labextension/static/568.c39998ba705e1f38a7c0.js
jupyterlab_theme_christmas/labextension/static/remoteEntry.59131672fff6cc48ab8d.js
jupyterlab_theme_christmas/labextension/static/style.js
jupyterlab_theme_christmas/labextension/themes/@datalayer-jupyter/jupyterlab-theme-christmas/index.css
jupyterlab_theme_christmas/labextension/themes/@datalayer-jupyter/jupyterlab-theme-christmas/index.js
jupyterlab_theme_christmas-0.1.2.data/data/share/jupyter/labextensions/@datalayer-jupyter/jupyterlab-theme-christmas/install.json
jupyterlab_theme_christmas-0.1.2.data/data/share/jupyter/labextensions/@datalayer-jupyter/jupyterlab-theme-christmas/package.json
jupyterlab_theme_christmas-0.1.2.data/data/share/jupyter/labextensions/@datalayer-jupyter/jupyterlab-theme-christmas/static/549.44cd2634f9cdc174fda1.js
jupyterlab_theme_christmas-0.1.2.data/data/share/jupyter/labextensions/@datalayer-jupyter/jupyterlab-theme-christmas/static/568.c39998ba705e1f38a7c0.js
jupyterlab_theme_christmas-0.1.2.data/data/share/jupyter/labextensions/@datalayer-jupyter/jupyterlab-theme-christmas/static/remoteEntry.59131672fff6cc48ab8d.js
jupyterlab_theme_christmas-0.1.2.data/data/share/jupyter/labextensions/@datalayer-jupyter/jupyterlab-theme-christmas/static/style.js
jupyterlab_theme_christmas-0.1.2.data/data/share/jupyter/labextensions/@datalayer-jupyter/jupyterlab-theme-christmas/themes/@datalayer-jupyter/jupyterlab-theme-christmas/index.css
jupyterlab_theme_christmas-0.1.2.data/data/share/jupyter/labextensions/@datalayer-jupyter/jupyterlab-theme-christmas/themes/@datalayer-jupyter/jupyterlab-theme-christmas/index.js
jupyterlab_theme_christmas-0.1.2.dist-info/LICENSE
jupyterlab_theme_christmas-0.1.2.dist-info/METADATA
jupyterlab_theme_christmas-0.1.2.dist-info/WHEEL
jupyterlab_theme_christmas-0.1.2.dist-info/top_level.txt
jupyterlab_theme_christmas-0.1.2.dist-info/RECORD
